{
  "template_name": "2",
  "processed_at": "2026-04-27T15:32:39",
  "pages_processed": 33,
  "pages_modified": 0,
  "detected_brands": [
    "Horizon Dream Home",
    "Darion Homes",
    "Archetype",
    "UiXSHUVO",
    "Hanuman",
    "Horizon",
    "ARCHERA",
    "Darion",
    "ACTURA",
    "Actura",
    "Solara",
    "Homzen",
    "Browed"
  ],
  "detected_emails": [],
  "detected_phones": [
    "2 0 0 1-2.18 2 19.79 19.79 0 0 1-8.63-3.07 19.5 19.5 0 0 1-6-6 19.79 19.79 0 0"
  ],
  "placeholder_mappings": [],
  "errors": []
}